README.rst
setup.py
pg_hotcache/__init__.py
pg_hotcache/core.py
pg_hotcache.egg-info/PKG-INFO
pg_hotcache.egg-info/SOURCES.txt
pg_hotcache.egg-info/dependency_links.txt
pg_hotcache.egg-info/entry_points.txt
pg_hotcache.egg-info/requires.txt
pg_hotcache.egg-info/top_level.txt