Metadata-Version: 1.1
Name: pg-hotcache
Version: 0.2.1
Summary: Loading into cache from said PostgreSQL database the tables, which are most frequently scanned.
Home-page: https://github.com/xtimon/pg_hotcache
Author: Timur Isanov
Author-email: tisanov@yahoo.com
License: MIT
Platform: UNKNOWN
Classifier: Environment :: Console
Classifier: Topic :: Database
Classifier: License :: OSI Approved :: MIT License
Classifier: Programming Language :: Python :: 2.6
Classifier: Programming Language :: Python :: 2.7
Classifier: Programming Language :: Python :: 3
